{
  "closed": 14,
  "data": [
    {
      "id": "I_kwDODqGIis5o7b9e",
      "closed": true,
      "title": "cannot get github project data , error in git_data_fetch.mjs  \"{} {} Error occured in pinned projects 2 {} {}\"",
      "createdAt": "2023-06-16T11:14:16Z",
      "url": "https://github.com/ashutosh1919/masterPortfolio/issues/301",
      "number": 301,
      "assignees": {
        "nodes": []
      },
      "repository": {
        "name": "masterPortfolio",
        "url": "https://github.com/ashutosh1919/masterPortfolio",
        "owner": {
          "login": "ashutosh1919",
          "avatarUrl": "https://avatars.githubusercontent.com/u/20843596?u=6deb5872cde2e3ab5bf5d48ece503bc8b5b0bcf6&v=4",
          "url": "https://github.com/ashutosh1919"
        }
      }
    },
    {
      "id": "I_kwDOI85XE85eP7Xl",
      "closed": false,
      "title": "Add Images here",
      "createdAt": "2023-02-12T12:06:29Z",
      "url": "https://github.com/AmanSarraf/ScreenShots/issues/1",
      "number": 1,
      "assignees": {
        "nodes": []
      },
      "repository": {
        "name": "ScreenShots",
        "url": "https://github.com/AmanSarraf/ScreenShots",
        "owner": {
          "login": "AmanSarraf",
          "avatarUrl": "https://avatars.githubusercontent.com/u/90839355?u=2d37e9951b1954c2899d53c89ebd82c1d6224138&v=4",
          "url": "https://github.com/AmanSarraf"
        }
      }
    },
    {
      "id": "I_kwDOGESZ9c5U1zsM",
      "closed": true,
      "title": "Resize the header background to properly fit in screen",
      "createdAt": "2022-10-26T03:44:12Z",
      "url": "https://github.com/AmanSarraf/Opensource-Buddy/issues/78",
      "number": 78,
      "assignees": {
        "nodes": [
          {
            "avatarUrl": "https://avatars.githubusercontent.com/u/102437896?u=511eeb5ba0a913f4ed84bd6317fa394d34c2e8f7&v=4",
            "name": null,
            "url": "https://github.com/GitArya27"
          }
        ]
      },
      "repository": {
        "name": "Opensource-Buddy",
        "url": "https://github.com/AmanSarraf/Opensource-Buddy",
        "owner": {
          "login": "AmanSarraf",
          "avatarUrl": "https://avatars.githubusercontent.com/u/90839355?u=2d37e9951b1954c2899d53c89ebd82c1d6224138&v=4",
          "url": "https://github.com/AmanSarraf"
        }
      }
    },
    {
      "id": "I_kwDOGESZ9c5UbqYK",
      "closed": false,
      "title": "[ADD] Option to connect with the community",
      "createdAt": "2022-10-20T12:29:37Z",
      "url": "https://github.com/AmanSarraf/Opensource-Buddy/issues/52",
      "number": 52,
      "assignees": {
        "nodes": [
          {
            "avatarUrl": "https://avatars.githubusercontent.com/u/43440929?u=b74bef8057c36171285e7e1da8f7728cc1b98ef0&v=4",
            "name": "Emmanuel Kolawole",
            "url": "https://github.com/sleekyom"
          }
        ]
      },
      "repository": {
        "name": "Opensource-Buddy",
        "url": "https://github.com/AmanSarraf/Opensource-Buddy",
        "owner": {
          "login": "AmanSarraf",
          "avatarUrl": "https://avatars.githubusercontent.com/u/90839355?u=2d37e9951b1954c2899d53c89ebd82c1d6224138&v=4",
          "url": "https://github.com/AmanSarraf"
        }
      }
    },
    {
      "id": "I_kwDOGESZ9c5UboSu",
      "closed": false,
      "title": "Add contributors badges to website, from README.md ",
      "createdAt": "2022-10-20T12:23:42Z",
      "url": "https://github.com/AmanSarraf/Opensource-Buddy/issues/51",
      "number": 51,
      "assignees": {
        "nodes": [
          {
            "avatarUrl": "https://avatars.githubusercontent.com/u/43440929?u=b74bef8057c36171285e7e1da8f7728cc1b98ef0&v=4",
            "name": "Emmanuel Kolawole",
            "url": "https://github.com/sleekyom"
          }
        ]
      },
      "repository": {
        "name": "Opensource-Buddy",
        "url": "https://github.com/AmanSarraf/Opensource-Buddy",
        "owner": {
          "login": "AmanSarraf",
          "avatarUrl": "https://avatars.githubusercontent.com/u/90839355?u=2d37e9951b1954c2899d53c89ebd82c1d6224138&v=4",
          "url": "https://github.com/AmanSarraf"
        }
      }
    },
    {
      "id": "I_kwDOGESZ9c5TzixF",
      "closed": true,
      "title": "[Suggestion] Design Ideas for announcement / notification bar",
      "createdAt": "2022-10-12T11:10:10Z",
      "url": "https://github.com/AmanSarraf/Opensource-Buddy/issues/30",
      "number": 30,
      "assignees": {
        "nodes": [
          {
            "avatarUrl": "https://avatars.githubusercontent.com/u/90839355?u=2d37e9951b1954c2899d53c89ebd82c1d6224138&v=4",
            "name": "Aman Kumar Sarraf",
            "url": "https://github.com/AmanSarraf"
          }
        ]
      },
      "repository": {
        "name": "Opensource-Buddy",
        "url": "https://github.com/AmanSarraf/Opensource-Buddy",
        "owner": {
          "login": "AmanSarraf",
          "avatarUrl": "https://avatars.githubusercontent.com/u/90839355?u=2d37e9951b1954c2899d53c89ebd82c1d6224138&v=4",
          "url": "https://github.com/AmanSarraf"
        }
      }
    },
    {
      "id": "I_kwDOGESZ9c5Tzitf",
      "closed": false,
      "title": "[Suggestion] Design Ideas for announcement / notification bar",
      "createdAt": "2022-10-12T11:09:59Z",
      "url": "https://github.com/AmanSarraf/Opensource-Buddy/issues/29",
      "number": 29,
      "assignees": {
        "nodes": [
          {
            "avatarUrl": "https://avatars.githubusercontent.com/u/90839355?u=2d37e9951b1954c2899d53c89ebd82c1d6224138&v=4",
            "name": "Aman Kumar Sarraf",
            "url": "https://github.com/AmanSarraf"
          }
        ]
      },
      "repository": {
        "name": "Opensource-Buddy",
        "url": "https://github.com/AmanSarraf/Opensource-Buddy",
        "owner": {
          "login": "AmanSarraf",
          "avatarUrl": "https://avatars.githubusercontent.com/u/90839355?u=2d37e9951b1954c2899d53c89ebd82c1d6224138&v=4",
          "url": "https://github.com/AmanSarraf"
        }
      }
    },
    {
      "id": "I_kwDOGESZ9c5TqkUt",
      "closed": true,
      "title": "[BUG] Adjust the hover effect on programs page",
      "createdAt": "2022-10-10T20:18:42Z",
      "url": "https://github.com/AmanSarraf/Opensource-Buddy/issues/21",
      "number": 21,
      "assignees": {
        "nodes": [
          {
            "avatarUrl": "https://avatars.githubusercontent.com/u/57594891?u=b70bc97e679a766791c01f17b71531a6faa57b3e&v=4",
            "name": "Pranav Rustagi",
            "url": "https://github.com/Pranav-Rustagi"
          }
        ]
      },
      "repository": {
        "name": "Opensource-Buddy",
        "url": "https://github.com/AmanSarraf/Opensource-Buddy",
        "owner": {
          "login": "AmanSarraf",
          "avatarUrl": "https://avatars.githubusercontent.com/u/90839355?u=2d37e9951b1954c2899d53c89ebd82c1d6224138&v=4",
          "url": "https://github.com/AmanSarraf"
        }
      }
    },
    {
      "id": "I_kwDOGESZ9c5TqeKL",
      "closed": true,
      "title": "Beautify the community section",
      "createdAt": "2022-10-10T19:54:57Z",
      "url": "https://github.com/AmanSarraf/Opensource-Buddy/issues/19",
      "number": 19,
      "assignees": {
        "nodes": [
          {
            "avatarUrl": "https://avatars.githubusercontent.com/u/75956011?u=15ac2b93a78d8e480a4aed8fbdd0acda5848f141&v=4",
            "name": "Maryam Momoh",
            "url": "https://github.com/Maryam-Momoh"
          }
        ]
      },
      "repository": {
        "name": "Opensource-Buddy",
        "url": "https://github.com/AmanSarraf/Opensource-Buddy",
        "owner": {
          "login": "AmanSarraf",
          "avatarUrl": "https://avatars.githubusercontent.com/u/90839355?u=2d37e9951b1954c2899d53c89ebd82c1d6224138&v=4",
          "url": "https://github.com/AmanSarraf"
        }
      }
    },
    {
      "id": "I_kwDOGESZ9c5TqcPw",
      "closed": true,
      "title": "Add a blog button on navigation",
      "createdAt": "2022-10-10T19:47:12Z",
      "url": "https://github.com/AmanSarraf/Opensource-Buddy/issues/18",
      "number": 18,
      "assignees": {
        "nodes": [
          {
            "avatarUrl": "https://avatars.githubusercontent.com/u/92772172?u=c3af9adc5f1d1ba951be469b9b9188feb174e93d&v=4",
            "name": "AMAN KUMAR",
            "url": "https://github.com/AmanKumar2626"
          }
        ]
      },
      "repository": {
        "name": "Opensource-Buddy",
        "url": "https://github.com/AmanSarraf/Opensource-Buddy",
        "owner": {
          "login": "AmanSarraf",
          "avatarUrl": "https://avatars.githubusercontent.com/u/90839355?u=2d37e9951b1954c2899d53c89ebd82c1d6224138&v=4",
          "url": "https://github.com/AmanSarraf"
        }
      }
    },
    {
      "id": "I_kwDOGESZ9c5TLscM",
      "closed": true,
      "title": "Remove my teams section and add suggest something more meaningful",
      "createdAt": "2022-10-04T02:26:42Z",
      "url": "https://github.com/AmanSarraf/Opensource-Buddy/issues/5",
      "number": 5,
      "assignees": {
        "nodes": [
          {
            "avatarUrl": "https://avatars.githubusercontent.com/u/57594891?u=b70bc97e679a766791c01f17b71531a6faa57b3e&v=4",
            "name": "Pranav Rustagi",
            "url": "https://github.com/Pranav-Rustagi"
          }
        ]
      },
      "repository": {
        "name": "Opensource-Buddy",
        "url": "https://github.com/AmanSarraf/Opensource-Buddy",
        "owner": {
          "login": "AmanSarraf",
          "avatarUrl": "https://avatars.githubusercontent.com/u/90839355?u=2d37e9951b1954c2899d53c89ebd82c1d6224138&v=4",
          "url": "https://github.com/AmanSarraf"
        }
      }
    },
    {
      "id": "I_kwDOGESZ9c5TLsG9",
      "closed": true,
      "title": "Guide to geneerate a live preview of project on local system",
      "createdAt": "2022-10-04T02:24:33Z",
      "url": "https://github.com/AmanSarraf/Opensource-Buddy/issues/4",
      "number": 4,
      "assignees": {
        "nodes": [
          {
            "avatarUrl": "https://avatars.githubusercontent.com/u/102357739?u=36c9cc482dbb0174a2035a3e7da95a5a5139c1a5&v=4",
            "name": "Soumyajit Brahma ",
            "url": "https://github.com/cleverhare"
          }
        ]
      },
      "repository": {
        "name": "Opensource-Buddy",
        "url": "https://github.com/AmanSarraf/Opensource-Buddy",
        "owner": {
          "login": "AmanSarraf",
          "avatarUrl": "https://avatars.githubusercontent.com/u/90839355?u=2d37e9951b1954c2899d53c89ebd82c1d6224138&v=4",
          "url": "https://github.com/AmanSarraf"
        }
      }
    },
    {
      "id": "I_kwDOGESZ9c5TLrS0",
      "closed": false,
      "title": "Update the README.md",
      "createdAt": "2022-10-04T02:19:03Z",
      "url": "https://github.com/AmanSarraf/Opensource-Buddy/issues/3",
      "number": 3,
      "assignees": {
        "nodes": [
          {
            "avatarUrl": "https://avatars.githubusercontent.com/u/102357739?u=36c9cc482dbb0174a2035a3e7da95a5a5139c1a5&v=4",
            "name": "Soumyajit Brahma ",
            "url": "https://github.com/cleverhare"
          }
        ]
      },
      "repository": {
        "name": "Opensource-Buddy",
        "url": "https://github.com/AmanSarraf/Opensource-Buddy",
        "owner": {
          "login": "AmanSarraf",
          "avatarUrl": "https://avatars.githubusercontent.com/u/90839355?u=2d37e9951b1954c2899d53c89ebd82c1d6224138&v=4",
          "url": "https://github.com/AmanSarraf"
        }
      }
    },
    {
      "id": "I_kwDOEOGY2M5N8UOR",
      "closed": true,
      "title": "Please invite me to the GitHub Community Organization",
      "createdAt": "2022-07-18T09:31:10Z",
      "url": "https://github.com/EddieHubCommunity/support/issues/4656",
      "number": 4656,
      "assignees": {
        "nodes": []
      },
      "repository": {
        "name": "support",
        "url": "https://github.com/EddieHubCommunity/support",
        "owner": {
          "login": "EddieHubCommunity",
          "avatarUrl": "https://avatars.githubusercontent.com/u/66388388?v=4",
          "url": "https://github.com/EddieHubCommunity"
        }
      }
    },
    {
      "id": "I_kwDOAxF--s5N3e6n",
      "closed": true,
      "title": "[hi] Translate docs/concepts/overview/components.md into Hindi",
      "createdAt": "2022-07-15T19:03:55Z",
      "url": "https://github.com/kubernetes/website/issues/35063",
      "number": 35063,
      "assignees": {
        "nodes": [
          {
            "avatarUrl": "https://avatars.githubusercontent.com/u/86051118?u=e034f658960ca6390b11662c5dec3db531aef265&v=4",
            "name": "Nitish Kumar",
            "url": "https://github.com/nitishfy"
          },
          {
            "avatarUrl": "https://avatars.githubusercontent.com/u/90839355?u=2d37e9951b1954c2899d53c89ebd82c1d6224138&v=4",
            "name": "Aman Kumar Sarraf",
            "url": "https://github.com/AmanSarraf"
          }
        ]
      },
      "repository": {
        "name": "website",
        "url": "https://github.com/kubernetes/website",
        "owner": {
          "login": "kubernetes",
          "avatarUrl": "https://avatars.githubusercontent.com/u/13629408?v=4",
          "url": "https://github.com/kubernetes"
        }
      }
    },
    {
      "id": "I_kwDOHJ_zcM5Ndsj8",
      "closed": false,
      "title": "I need a video Screencast",
      "createdAt": "2022-07-09T09:37:51Z",
      "url": "https://github.com/AmanSarraf/Images-in-README/issues/2",
      "number": 2,
      "assignees": {
        "nodes": []
      },
      "repository": {
        "name": "Images-in-README",
        "url": "https://github.com/AmanSarraf/Images-in-README",
        "owner": {
          "login": "AmanSarraf",
          "avatarUrl": "https://avatars.githubusercontent.com/u/90839355?u=2d37e9951b1954c2899d53c89ebd82c1d6224138&v=4",
          "url": "https://github.com/AmanSarraf"
        }
      }
    },
    {
      "id": "I_kwDOHj6gPM5M_jmR",
      "closed": false,
      "title": "running ping-to-sockeye.yaml throws deafault link ",
      "createdAt": "2022-07-01T18:43:01Z",
      "url": "https://github.com/JeffNeff/Triggermesh-Quick-Start/issues/8",
      "number": 8,
      "assignees": {
        "nodes": []
      },
      "repository": {
        "name": "Triggermesh-Quick-Start",
        "url": "https://github.com/JeffNeff/Triggermesh-Quick-Start",
        "owner": {
          "login": "JeffNeff",
          "avatarUrl": "https://avatars.githubusercontent.com/u/60796676?u=c54a13fd4e4160d8432a9426ba7fca75d5b16877&v=4",
          "url": "https://github.com/JeffNeff"
        }
      }
    },
    {
      "id": "I_kwDOA1vjzM5Mc-ZF",
      "closed": true,
      "title": "Cannot start Minikube on Ubuntu using docker desktop vm",
      "createdAt": "2022-06-23T16:28:01Z",
      "url": "https://github.com/kubernetes/minikube/issues/14402",
      "number": 14402,
      "assignees": {
        "nodes": []
      },
      "repository": {
        "name": "minikube",
        "url": "https://github.com/kubernetes/minikube",
        "owner": {
          "login": "kubernetes",
          "avatarUrl": "https://avatars.githubusercontent.com/u/13629408?v=4",
          "url": "https://github.com/kubernetes"
        }
      }
    },
    {
      "id": "I_kwDOHbolN85MCoZu",
      "closed": true,
      "title": "Using Azure SDK for using computer vision service",
      "createdAt": "2022-06-18T10:42:11Z",
      "url": "https://github.com/AmanSarraf/Go-Project/issues/10",
      "number": 10,
      "assignees": {
        "nodes": [
          {
            "avatarUrl": "https://avatars.githubusercontent.com/u/90839355?u=2d37e9951b1954c2899d53c89ebd82c1d6224138&v=4",
            "name": "Aman Kumar Sarraf",
            "url": "https://github.com/AmanSarraf"
          }
        ]
      },
      "repository": {
        "name": "Go-Project",
        "url": "https://github.com/AmanSarraf/Go-Project",
        "owner": {
          "login": "AmanSarraf",
          "avatarUrl": "https://avatars.githubusercontent.com/u/90839355?u=2d37e9951b1954c2899d53c89ebd82c1d6224138&v=4",
          "url": "https://github.com/AmanSarraf"
        }
      }
    },
    {
      "id": "I_kwDODHB8b85Hma39",
      "closed": true,
      "title": "[Doc] Documentation Related ",
      "createdAt": "2022-04-12T07:08:37Z",
      "url": "https://github.com/apache/eventmesh/issues/830",
      "number": 830,
      "assignees": {
        "nodes": [
          {
            "avatarUrl": "https://avatars.githubusercontent.com/u/90839355?u=2d37e9951b1954c2899d53c89ebd82c1d6224138&v=4",
            "name": "Aman Kumar Sarraf",
            "url": "https://github.com/AmanSarraf"
          }
        ]
      },
      "repository": {
        "name": "eventmesh",
        "url": "https://github.com/apache/eventmesh",
        "owner": {
          "login": "apache",
          "avatarUrl": "https://avatars.githubusercontent.com/u/47359?v=4",
          "url": "https://github.com/apache"
        }
      }
    },
    {
      "id": "I_kwDOHJ_zcM5HfeRb",
      "closed": false,
      "title": "I need a screenshot",
      "createdAt": "2022-04-11T06:00:36Z",
      "url": "https://github.com/AmanSarraf/Images-in-README/issues/1",
      "number": 1,
      "assignees": {
        "nodes": []
      },
      "repository": {
        "name": "Images-in-README",
        "url": "https://github.com/AmanSarraf/Images-in-README",
        "owner": {
          "login": "AmanSarraf",
          "avatarUrl": "https://avatars.githubusercontent.com/u/90839355?u=2d37e9951b1954c2899d53c89ebd82c1d6224138&v=4",
          "url": "https://github.com/AmanSarraf"
        }
      }
    },
    {
      "id": "I_kwDOE8KVf85FCnmI",
      "closed": true,
      "title": "OOP concept (Polymorphism)",
      "createdAt": "2022-03-03T11:49:02Z",
      "url": "https://github.com/Lakhankumawat/LearnCPP/issues/276",
      "number": 276,
      "assignees": {
        "nodes": [
          {
            "avatarUrl": "https://avatars.githubusercontent.com/u/90839355?u=2d37e9951b1954c2899d53c89ebd82c1d6224138&v=4",
            "name": "Aman Kumar Sarraf",
            "url": "https://github.com/AmanSarraf"
          }
        ]
      },
      "repository": {
        "name": "LearnCPP",
        "url": "https://github.com/Lakhankumawat/LearnCPP",
        "owner": {
          "login": "Lakhankumawat",
          "avatarUrl": "https://avatars.githubusercontent.com/u/55774240?u=31e7af397c336086bf423b5c2a7a64a8fff0548f&v=4",
          "url": "https://github.com/Lakhankumawat"
        }
      }
    }
  ],
  "open": 8,
  "totalCount": 22
}
